[ {
  "id" : {
    "queryId" : "Q_PERSANOO_FF85",
    "version" : "1.0.0"
  },
  "name" : "PersonaQuery",
  "sqlWhere" : null,
  "customizationLayer" : 0,
  "customizationLayerDescription" : "ECU",
  "mainEntityId" : "EN_PERSONAHF_537",
  "mainEntityVersion" : "1.0.0",
  "queryMembers" : [ {
    "alias" : "nombre",
    "attribute" : {
      "attributeId" : "AT46_NOMBRELV537",
      "autoGenerated" : false,
      "autoGeneratedStr" : "F",
      "columnName" : null,
      "customizationLayer" : 0,
      "customizationLayerDescription" : "ECU",
      "dataType" : "String",
      "entityPk" : {
        "entityId" : "EN_PERSONAHF_537",
        "version" : "1.0.0"
      },
      "expression" : null,
      "falseValue" : null,
      "label" : null,
      "labelId" : null,
      "length" : 30,
      "listValues" : null,
      "name" : "nombre",
      "objectType" : null,
      "order" : 1,
      "pk" : false,
      "pkStr" : "F",
      "required" : false,
      "requiredStr" : "F",
      "transient" : false,
      "transientStr" : "F",
      "trueValue" : null
    },
    "customizationLayer" : 0,
    "customizationLayerDescription" : "",
    "defaultValue" : null,
    "defaultValueDataType" : null,
    "function" : null,
    "label" : null,
    "operator" : null,
    "order" : 3,
    "orderBy" : 0,
    "orderByDirection" : null,
    "queryMemberId" : "QM_PERSA55O5F559_03",
    "select" : true,
    "selectStr" : "T",
    "where" : false,
    "whereStr" : "F"
  }, {
    "alias" : "nombreC",
    "attribute" : {
      "attributeId" : "AT46_NOMBRECC537",
      "autoGenerated" : false,
      "autoGeneratedStr" : "F",
      "columnName" : null,
      "customizationLayer" : 0,
      "customizationLayerDescription" : "ECU",
      "dataType" : "String",
      "entityPk" : {
        "entityId" : "EN_PERSONAHF_537",
        "version" : "1.0.0"
      },
      "expression" : null,
      "falseValue" : null,
      "label" : null,
      "labelId" : null,
      "length" : 30,
      "listValues" : null,
      "name" : "nombreC",
      "objectType" : null,
      "order" : 7,
      "pk" : false,
      "pkStr" : "F",
      "required" : false,
      "requiredStr" : "F",
      "transient" : false,
      "transientStr" : "F",
      "trueValue" : null
    },
    "customizationLayer" : 0,
    "customizationLayerDescription" : null,
    "defaultValue" : null,
    "defaultValueDataType" : null,
    "function" : null,
    "label" : null,
    "operator" : null,
    "order" : 2000,
    "orderBy" : 0,
    "orderByDirection" : "A",
    "queryMemberId" : "QM_PERSA5NONF246_01",
    "select" : true,
    "selectStr" : "T",
    "where" : false,
    "whereStr" : "F"
  }, {
    "alias" : "sexo",
    "attribute" : {
      "attributeId" : "AT66_SEXOXTUC537",
      "autoGenerated" : false,
      "autoGeneratedStr" : "F",
      "columnName" : null,
      "customizationLayer" : 0,
      "customizationLayerDescription" : "ECU",
      "dataType" : "String",
      "entityPk" : {
        "entityId" : "EN_PERSONAHF_537",
        "version" : "1.0.0"
      },
      "expression" : null,
      "falseValue" : null,
      "label" : null,
      "labelId" : null,
      "length" : 30,
      "listValues" : null,
      "name" : "sexo",
      "objectType" : null,
      "order" : 5,
      "pk" : false,
      "pkStr" : "F",
      "required" : false,
      "requiredStr" : "F",
      "transient" : false,
      "transientStr" : "F",
      "trueValue" : null
    },
    "customizationLayer" : 0,
    "customizationLayerDescription" : null,
    "defaultValue" : null,
    "defaultValueDataType" : null,
    "function" : null,
    "label" : null,
    "operator" : null,
    "order" : 2000,
    "orderBy" : 0,
    "orderByDirection" : "A",
    "queryMemberId" : "QM_PERSAFF5FF341_02",
    "select" : true,
    "selectStr" : "T",
    "where" : false,
    "whereStr" : "F"
  }, {
    "alias" : "estado",
    "attribute" : {
      "attributeId" : "AT97_ESTADOUB537",
      "autoGenerated" : false,
      "autoGeneratedStr" : "F",
      "columnName" : null,
      "customizationLayer" : 0,
      "customizationLayerDescription" : "ECU",
      "dataType" : "String",
      "entityPk" : {
        "entityId" : "EN_PERSONAHF_537",
        "version" : "1.0.0"
      },
      "expression" : null,
      "falseValue" : null,
      "label" : null,
      "labelId" : null,
      "length" : 30,
      "listValues" : null,
      "name" : "estado",
      "objectType" : null,
      "order" : 6,
      "pk" : false,
      "pkStr" : "F",
      "required" : false,
      "requiredStr" : "F",
      "transient" : false,
      "transientStr" : "F",
      "trueValue" : null
    },
    "customizationLayer" : 0,
    "customizationLayerDescription" : null,
    "defaultValue" : null,
    "defaultValueDataType" : null,
    "function" : null,
    "label" : null,
    "operator" : null,
    "order" : 2000,
    "orderBy" : 0,
    "orderByDirection" : "A",
    "queryMemberId" : "QM_PERSANF8OF393_04",
    "select" : true,
    "selectStr" : "T",
    "where" : false,
    "whereStr" : "F"
  }, {
    "alias" : "apellidoC",
    "attribute" : {
      "attributeId" : "AT80_APELLIOD537",
      "autoGenerated" : false,
      "autoGeneratedStr" : "F",
      "columnName" : null,
      "customizationLayer" : 0,
      "customizationLayerDescription" : "ECU",
      "dataType" : "String",
      "entityPk" : {
        "entityId" : "EN_PERSONAHF_537",
        "version" : "1.0.0"
      },
      "expression" : null,
      "falseValue" : null,
      "label" : null,
      "labelId" : null,
      "length" : 30,
      "listValues" : null,
      "name" : "apellidoC",
      "objectType" : null,
      "order" : 8,
      "pk" : false,
      "pkStr" : "F",
      "required" : false,
      "requiredStr" : "F",
      "transient" : false,
      "transientStr" : "F",
      "trueValue" : null
    },
    "customizationLayer" : 0,
    "customizationLayerDescription" : null,
    "defaultValue" : null,
    "defaultValueDataType" : null,
    "function" : null,
    "label" : null,
    "operator" : null,
    "order" : 2000,
    "orderBy" : 0,
    "orderByDirection" : "A",
    "queryMemberId" : "QM_PERSAOF55O108_03",
    "select" : true,
    "selectStr" : "T",
    "where" : false,
    "whereStr" : "F"
  }, {
    "alias" : "apellido",
    "attribute" : {
      "attributeId" : "AT33_APELLIDD537",
      "autoGenerated" : false,
      "autoGeneratedStr" : "F",
      "columnName" : null,
      "customizationLayer" : 0,
      "customizationLayerDescription" : "ECU",
      "dataType" : "String",
      "entityPk" : {
        "entityId" : "EN_PERSONAHF_537",
        "version" : "1.0.0"
      },
      "expression" : null,
      "falseValue" : null,
      "label" : null,
      "labelId" : null,
      "length" : 30,
      "listValues" : null,
      "name" : "apellido",
      "objectType" : null,
      "order" : 2,
      "pk" : false,
      "pkStr" : "F",
      "required" : false,
      "requiredStr" : "F",
      "transient" : false,
      "transientStr" : "F",
      "trueValue" : null
    },
    "customizationLayer" : 0,
    "customizationLayerDescription" : "",
    "defaultValue" : null,
    "defaultValueDataType" : null,
    "function" : null,
    "label" : null,
    "operator" : null,
    "order" : 2,
    "orderBy" : 0,
    "orderByDirection" : null,
    "queryMemberId" : "QM_PERSAOF88F481_02",
    "select" : true,
    "selectStr" : "T",
    "where" : false,
    "whereStr" : "F"
  }, {
    "alias" : "telefono",
    "attribute" : {
      "attributeId" : "AT56_TELEFOOO537",
      "autoGenerated" : false,
      "autoGeneratedStr" : "F",
      "columnName" : null,
      "customizationLayer" : 0,
      "customizationLayerDescription" : "ECU",
      "dataType" : "String",
      "entityPk" : {
        "entityId" : "EN_PERSONAHF_537",
        "version" : "1.0.0"
      },
      "expression" : null,
      "falseValue" : null,
      "label" : null,
      "labelId" : null,
      "length" : 30,
      "listValues" : null,
      "name" : "telefono",
      "objectType" : null,
      "order" : 3,
      "pk" : false,
      "pkStr" : "F",
      "required" : false,
      "requiredStr" : "F",
      "transient" : false,
      "transientStr" : "F",
      "trueValue" : null
    },
    "customizationLayer" : 0,
    "customizationLayerDescription" : "",
    "defaultValue" : null,
    "defaultValueDataType" : null,
    "function" : null,
    "label" : null,
    "operator" : null,
    "order" : 4,
    "orderBy" : 0,
    "orderByDirection" : null,
    "queryMemberId" : "QM_PERSAONFNO822_04",
    "select" : true,
    "selectStr" : "T",
    "where" : false,
    "whereStr" : "F"
  }, {
    "alias" : "idPersona",
    "attribute" : {
      "attributeId" : "AT24_IDPERSAN537",
      "autoGenerated" : false,
      "autoGeneratedStr" : "F",
      "columnName" : null,
      "customizationLayer" : 0,
      "customizationLayerDescription" : "ECU",
      "dataType" : "Integer",
      "entityPk" : {
        "entityId" : "EN_PERSONAHF_537",
        "version" : "1.0.0"
      },
      "expression" : null,
      "falseValue" : null,
      "label" : null,
      "labelId" : null,
      "length" : 0,
      "listValues" : null,
      "name" : "idPersona",
      "objectType" : null,
      "order" : 4,
      "pk" : false,
      "pkStr" : "F",
      "required" : false,
      "requiredStr" : "F",
      "transient" : false,
      "transientStr" : "F",
      "trueValue" : null
    },
    "customizationLayer" : 0,
    "customizationLayerDescription" : "",
    "defaultValue" : null,
    "defaultValueDataType" : null,
    "function" : null,
    "label" : null,
    "operator" : null,
    "order" : 1,
    "orderBy" : 0,
    "orderByDirection" : null,
    "queryMemberId" : "QM_PERSAONO88351_01",
    "select" : true,
    "selectStr" : "T",
    "where" : false,
    "whereStr" : "F"
  } ],
  "customEvents" : [ {
    "executionType" : 7,
    "customEventId" : "CEQY_130_Q_PERSANOO_FF85_863",
    "filter" : null,
    "customizationLayer" : 0,
    "customizationLayerDescription" : "ECU",
    "queryEventType" : {
      "eventId" : 130,
      "name" : "ExecuteQuery",
      "description" : "Sobreescribe la ejecución de un Query"
    },
    "eventActions" : [ {
      "actionId" : "BLI5819_bli_getpersonas",
      "actionType" : "BLI",
      "actionArgs" : [ ]
    }, {
      "actionId" : "CUSTOM",
      "actionType" : "CUSTOM",
      "actionArgs" : [ ]
    } ],
    "customizedEventType" : "INHERITED",
    "id" : null,
    "eventId" : 130
  } ],
  "isAutomatic" : false,
  "mainEntityModule" : "MMZJB"
} ]